offgas/__init__.py
offgas/_version.py
offgas/offgas.py
offgas-0.2.5.dist-info/LICENSE.txt
offgas-0.2.5.dist-info/METADATA
offgas-0.2.5.dist-info/WHEEL
offgas-0.2.5.dist-info/top_level.txt
offgas-0.2.5.dist-info/RECORD
