Metadata-Version: 2.1
Name: offgas
Version: 0.2.5
Summary: Python interface to the USB CO2 monitor
Home-page: https://github.com/Pinkers/offgas
Author: Aaron Kirby
Author-email: aaronkirby2000@gmail.com
License: MIT License
Download-URL: https://github.com/Pinkers/offgas/archive/v0.2.5.zip
Platform: UNKNOWN
Classifier: Programming Language :: Python :: 3
Requires-Dist: hidapi
Requires-Dist: future
Requires-Dist: pandas
